setup.py
gb_distn/Binomialdistribution.py
gb_distn/Gaussiandistribution.py
gb_distn/Generaldistribution.py
gb_distn/__init__.py
gb_distn.egg-info/PKG-INFO
gb_distn.egg-info/SOURCES.txt
gb_distn.egg-info/dependency_links.txt
gb_distn.egg-info/not-zip-safe
gb_distn.egg-info/top_level.txt